atlassian_modules/__init__.py
atlassian_modules/helper.py
atlassian_modules/jira_helper/__init__.py
atlassian_modules/jira_helper/attach_file_to_ticket.py
atlassian_modules/jira_helper/comment_ticket.py
atlassian_modules/jira_helper/create_custom_ticket.py
atlassian_modules/jira_helper/create_ticket.py
atlassian_modules/jira_helper/delete_ticket.py
atlassian_modules/jira_helper/get_ticket_subject.py
atlassian_modules/jira_helper/get_transitions.py
atlassian_modules/jira_helper/if_ticket_exist.py
atlassian_modules/jira_helper/jql_ticket.py
atlassian_modules/jira_helper/transition_ticket.py
atlassian_modules/jira_helper/update_ticket_with_fields.py
atlassian_modules/wiki_helper/__init__.py
atlassian_modules/wiki_helper/add_row_to_table.py
atlassian_modules/wiki_helper/add_toc_to_page.py
atlassian_modules/wiki_helper/create_page_from_template.py
atlassian_modules/wiki_helper/create_wiki_page.py
atlassian_modules/wiki_helper/duplicate_wiki_page.py
atlassian_modules/wiki_helper/get_child_pages_recursive.py
atlassian_modules/wiki_helper/get_page_content.py
atlassian_modules/wiki_helper/get_page_id.py
atlassian_modules/wiki_helper/get_parent_page_id.py
atlassian_modules/wiki_helper/get_tables_from_page.py
atlassian_modules/wiki_helper/move_wiki_page.py
atlassian_modules/wiki_helper/replace_in_page.py
atlassian_modules/wiki_helper/update_or_add_table_row.py
atlassian_modules/wiki_helper/update_page_content.py
atlassian_modules/wiki_helper/update_wiki_page.py
atlassian_modules/wiki_helper/wiki_page_exists.py
atlassian_modules-1.0.1.dist-info/METADATA
atlassian_modules-1.0.1.dist-info/WHEEL
atlassian_modules-1.0.1.dist-info/top_level.txt
atlassian_modules-1.0.1.dist-info/RECORD
