Metadata-Version: 2.2
Name: atlassian_modules
Version: 1.0.1
Summary: Modules for interacting with Atlassian cloud products.
Home-page: 
Author: Pavan Bhatt
Author-email: pavanhbhatt1@gmail.com
Requires-Dist: requests
Requires-Dist: beautifulsoup4
Dynamic: author
Dynamic: author-email
Dynamic: description
Dynamic: description-content-type
Dynamic: requires-dist
Dynamic: summary
